mdit/__init__.py
mdit/engines/__init__.py
mdit/engines/io.py
mdit/ml/__init__.py
mdit/orchestrator/__init__.py
mdit/processing/__init__.py
mdit/processing/pipelines/__init__.py
mdit/processing/quality/__init__.py
mdit/processing/transformations/__init__.py
mdit/session/__init__.py
modern_data_integration_tool-0.1.1.dist-info/LICENSE
modern_data_integration_tool-0.1.1.dist-info/METADATA
modern_data_integration_tool-0.1.1.dist-info/WHEEL
modern_data_integration_tool-0.1.1.dist-info/entry_points.txt
modern_data_integration_tool-0.1.1.dist-info/RECORD
