Metadata-Version: 2.1
Name: modern-data-integration-tool
Version: 0.1.1
Summary: A multiheaded modern data bridging package based on pipeline manifests to integrate between any modern (and old) data stack tools
License: MIT
Author: Carlos D. Escobar-Valbuena
Author-email: carlosdavidescobar@gmail.com
Requires-Python: >=3.10,<4.0
Classifier: License :: OSI Approved :: MIT License
Classifier: Programming Language :: Python :: 3
Classifier: Programming Language :: Python :: 3.10
Classifier: Programming Language :: Python :: 3.11
Requires-Dist: databricks-session (>=0.2.1,<0.3.0)
